{"otherData": {},"traceEvents":[{"cat":"function","dur":185411,"name":"glfwInit","ph":"X","pid":0,"tid":2351354327,"ts":21032139463},{"cat":"function","dur":98732,"name":"glfwCreateWindow","ph":"X","pid":0,"tid":2351354327,"ts":21032324894},{"cat":"function","dur":4015,"name":"virtual void Tabby::OpenGLContext::Init()","ph":"X","pid":0,"tid":2351354327,"ts":21032423683},{"cat":"function","dur":13,"name":"virtual void Tabby::MacWindow::SetVSync(bool)","ph":"X","pid":0,"tid":2351354327,"ts":21032427729},{"cat":"function","dur":288645,"name":"virtual void Tabby::MacWindow::Init(const Tabby::WindowProps &)","ph":"X","pid":0,"tid":2351354327,"ts":21032139103},{"cat":"function","dur":288650,"name":"Tabby::MacWindow::MacWindow(const Tabby::WindowProps &)","ph":"X","pid":0,"tid":2351354327,"ts":21032139103},{"cat":"function","dur":5,"name":"virtual void Tabby::OpenGLRendererAPI::Init()","ph":"X","pid":0,"tid":2351354327,"ts":21032427782},{"cat":"function","dur":1,"name":"Tabby::OpenGLVertexArray::OpenGLVertexArray()","ph":"X","pid":0,"tid":2351354327,"ts":21032427819},{"cat":"function","dur":4,"name":"virtual void Tabby::OpenGLVertexBuffer::Bind() const","ph":"X","pid":0,"tid":2351354327,"ts":21032427849},{"cat":"function","dur":19,"name":"Tabby::OpenGLVertexBuffer::OpenGLVertexBuffer(float *, uint32_t)","ph":"X","pid":0,"tid":2351354327,"ts":21032427848},{"cat":"function","dur":0,"name":"virtual void Tabby::OpenGLVertexBuffer::Bind() const","ph":"X","pid":0,"tid":2351354327,"ts":21032427882},{"cat":"function","dur":14,"name":"virtual void Tabby::OpenGLVertexArray::AddVertexBuffer(const Ref<Tabby::VertexBuffer> &)","ph":"X","pid":0,"tid":2351354327,"ts":21032427875},{"cat":"function","dur":3,"name":"Tabby::OpenGLIndexBuffer::OpenGLIndexBuffer(uint32_t *, uint32_t)","ph":"X","pid":0,"tid":2351354327,"ts":21032427894},{"cat":"function","dur":0,"name":"virtual void Tabby::OpenGLIndexBuffer::Bind() const","ph":"X","pid":0,"tid":2351354327,"ts":21032427902},{"cat":"function","dur":3,"name":"virtual void Tabby::OpenGLVertexArray::SetIndexBuffer(const Ref<Tabby::IndexBuffer> &)","ph":"X","pid":0,"tid":2351354327,"ts":21032427902},{"cat":"function","dur":7,"name":"Tabby::OpenGLTexture2D::OpenGLTexture2D(uint32_t, uint32_t)","ph":"X","pid":0,"tid":2351354327,"ts":21032427922},{"cat":"function","dur":80,"name":"virtual void Tabby::OpenGLTexture2D::SetData(void *, uint32_t)","ph":"X","pid":0,"tid":2351354327,"ts":21032427934},{"cat":"function","dur":16,"name":"std::string Tabby::OpenGLShader::ReadFile(const std::string &)","ph":"X","pid":0,"tid":2351354327,"ts":21032428033},{"cat":"function","dur":0,"name":"std::unordered_map<GLenum, std::string> Tabby::OpenGLShader::PreProcess(const std::string &)","ph":"X","pid":0,"tid":2351354327,"ts":21032428054},{"cat":"function","dur":373,"name":"void Tabby::OpenGLShader::Compile(std::unordered_map<GLenum, std::string> &)","ph":"X","pid":0,"tid":2351354327,"ts":21032428058},{"cat":"function","dur":408,"name":"Tabby::OpenGLShader::OpenGLShader(const std::string &)","ph":"X","pid":0,"tid":2351354327,"ts":21032428033},{"cat":"function","dur":4,"name":"virtual void Tabby::OpenGLShader::SetInt(const std::string &, int)","ph":"X","pid":0,"tid":2351354327,"ts":21032428446},{"cat":"function","dur":673,"name":"static void Tabby::Renderer::Init()","ph":"X","pid":0,"tid":2351354327,"ts":21032427781},{"cat":"function","dur":691,"name":"virtual void Tabby::ImGuiLayer::OnAttach()","ph":"X","pid":0,"tid":2351354327,"ts":21032428460},{"cat":"function","dur":709,"name":"void Tabby::Application::PushLayer(Tabby::Layer *)","ph":"X","pid":0,"tid":2351354327,"ts":21032428458},{"cat":"function","dur":290094,"name":"Tabby::Application::Application()","ph":"X","pid":0,"tid":2351354327,"ts":21032139078},{"cat":"function","dur":2,"name":"Tabby::OrthographicCamera::OrthographicCamera(float, float, float, float)","ph":"X","pid":0,"tid":2351354327,"ts":21032429192}